sharpe/__init__.py
sharpe/data/__init__.py
sharpe/data/alt.py
sharpe/data/db.py
sharpe/data/mkt.py
sharpe/data/model.py
sharpe/utils/__init__.py
sharpe/utils/constants.py
sharpe/utils/env.py
sharpe/utils/logger.py
sharpe/utils/options.py
sharpe/utils/time.py
sharpe/utils/universe.py
tensorfi_sharpe-0.1.15.dist-info/licenses/LICENSE
tensorfi_sharpe-0.1.15.dist-info/METADATA
tensorfi_sharpe-0.1.15.dist-info/WHEEL
tensorfi_sharpe-0.1.15.dist-info/top_level.txt
tensorfi_sharpe-0.1.15.dist-info/RECORD
