Metadata-Version: 2.4
Name: tensorfi-sharpe
Version: 0.1.15
Summary: Financial data access and analysis library with market data, options calculations, and database integration
Home-page: https://github.com/wang-sanity/sharpe
Author: rwang
Author-email: 
License: CC BY-NC 4.0
Project-URL: Homepage, https://github.com/wang-sanity/sharpe
Project-URL: Documentation, https://github.com/wang-sanity/sharpe/docs
Project-URL: Repository, https://github.com/wang-sanity/sharpe
Project-URL: Bug Tracker, https://github.com/wang-sanity/sharpe/issues
Keywords: finance,markets,data,options,database,analysis
Classifier: Development Status :: 4 - Beta
Classifier: Intended Audience :: Financial and Insurance Industry
Classifier: Intended Audience :: Developers
Classifier: License :: Other/Proprietary License
Classifier: Programming Language :: Python :: 3
Classifier: Programming Language :: Python :: 3.11
Classifier: Programming Language :: Python :: 3.12
Classifier: Topic :: Office/Business :: Financial
Classifier: Topic :: Scientific/Engineering :: Information Analysis
Requires-Python: >=3.11
License-File: LICENSE
Requires-Dist: pandas>=1.5.0
Requires-Dist: numpy>=1.24.0
Requires-Dist: scipy>=1.6.0
Requires-Dist: sqlalchemy>=2.0.0
Requires-Dist: asyncpg>=0.28.0
Requires-Dist: requests>=2.28.0
Requires-Dist: aiohttp>=3.8.0
Requires-Dist: beautifulsoup4>=4.11.0
Requires-Dist: boto3>=1.26.0
Requires-Dist: pandas_market_calendars>=4.0.0
Requires-Dist: pytz>=2022.7
Requires-Dist: python-dotenv>=1.0.0
Requires-Dist: pyyaml>=6.0
Requires-Dist: tqdm>=4.64.0
Provides-Extra: dev
Requires-Dist: pytest>=7.0.0; extra == "dev"
Requires-Dist: pytest-cov>=4.0.0; extra == "dev"
Requires-Dist: pytest-playwright>=0.3.0; extra == "dev"
Requires-Dist: black>=23.0.0; extra == "dev"
Requires-Dist: pre-commit>=3.0.0; extra == "dev"
Dynamic: home-page
Dynamic: license-file
Dynamic: requires-python
